prepesthel/__init__.py
prepesthel/_version.py
prepesthel/io.py
prepesthel/participant.py
prepesthel/runner.py
prepesthel-0.1.1.dist-info/LICENSE
prepesthel-0.1.1.dist-info/METADATA
prepesthel-0.1.1.dist-info/WHEEL
prepesthel-0.1.1.dist-info/top_level.txt
prepesthel-0.1.1.dist-info/RECORD
