Metadata-Version: 2.2
Name: prepesthel
Version: 0.1.1
Summary: PREcice-PErformance-STudy-HELpers: Python tools for conducting parameter studies and automating workflows in preCICE tutorial cases.
Author-email: Benjamin Rodenberg <benjamin.rodenberg@cit.tum.de>
License:                     GNU GENERAL PUBLIC LICENSE
Project-URL: Homepage, https://github.com/BenjaminRodenberg/doConvergenceStudy
Project-URL: Source, https://github.com/BenjaminRodenberg/doConvergenceStudy
Project-URL: Tracker, https://github.com/BenjaminRodenberg/doConvergenceStudy/issues
Keywords: preCICE,parameter studies,convergence,automation,Python
Classifier: Development Status :: 3 - Alpha
Classifier: Intended Audience :: Developers
Classifier: License :: OSI Approved :: GNU General Public License v3 (GPLv3)
Classifier: Programming Language :: Python :: 3
Classifier: Topic :: Scientific/Engineering :: Mathematics
Classifier: Topic :: Software Development :: Libraries :: Python Modules
License-File: LICENSE
Requires-Dist: numpy
Requires-Dist: GitPython
